{
	"info": {
		"_postman_id": "8812edd2-be4e-4877-a935-a38c4170b4bd",
		"name": "AI Ticketing System",
		"schema": "https://schema.getpostman.com/json/collection/v2.1.0/collection.json",
		"_exporter_id": "43819293",
		"_collection_link": "https://samyakrajsubedi.postman.co/workspace/Samyak-Raj-Subedi's-Workspace~b3afd5f4-f828-461d-8e85-1ceee5cd5af2/collection/43819293-8812edd2-be4e-4877-a935-a38c4170b4bd?action=share&source=collection_link&creator=43819293"
	},
	"item": [
		{
			"name": "User Routes",
			"item": [
				{
					"name": "register",
					"request": {
						"method": "POST",
						"header": [],
						"body": {
							"mode": "raw",
							"raw": " { \"email\" : \"samyak@ai.test.com\", \"password\" : \"CLEB1197B2\"  }",
							"options": {
								"raw": {
									"language": "json"
								}
							}
						},
						"url": {
							"raw": "http://localhost:3000/api/auth/register",
							"protocol": "http",
							"host": [
								"localhost"
							],
							"port": "3000",
							"path": [
								"api",
								"auth",
								"register"
							]
						}
					},
					"response": []
				},
				{
					"name": "login",
					"request": {
						"method": "POST",
						"header": [],
						"body": {
							"mode": "raw",
							"raw": " { \"email\" : \"samyak@admin.test.com\", \"password\" : \"CLEB1197B2\"  }",
							"options": {
								"raw": {
									"language": "json"
								}
							}
						},
						"url": {
							"raw": "http://localhost:3000/api/auth/login",
							"protocol": "http",
							"host": [
								"localhost"
							],
							"port": "3000",
							"path": [
								"api",
								"auth",
								"login"
							]
						}
					},
					"response": []
				},
				{
					"name": "logout",
					"request": {
						"method": "POST",
						"header": [],
						"url": {
							"raw": "http://localhost:3000/api/auth/logout",
							"protocol": "http",
							"host": [
								"localhost"
							],
							"port": "3000",
							"path": [
								"api",
								"auth",
								"logout"
							]
						}
					},
					"response": []
				},
				{
					"name": "update-user",
					"request": {
						"method": "POST",
						"header": [],
						"body": {
							"mode": "raw",
							"raw": "{ \"skills\" : [\"React\" , \"NextJs\"], \"role\" : \"moderator\", \"email\" :\"samyak@ai.test2.com\" }",
							"options": {
								"raw": {
									"language": "json"
								}
							}
						},
						"url": {
							"raw": "http://localhost:3000/api/auth/update-user",
							"protocol": "http",
							"host": [
								"localhost"
							],
							"port": "3000",
							"path": [
								"api",
								"auth",
								"update-user"
							]
						}
					},
					"response": []
				},
				{
					"name": "get-All-Users",
					"protocolProfileBehavior": {
						"disableBodyPruning": true
					},
					"request": {
						"method": "GET",
						"header": [],
						"body": {
							"mode": "raw",
							"raw": " { \"email\" : \"samyak@ai.test2.com\", \"password\" : \"CLEB1197B2\"  }"
						},
						"url": {
							"raw": "http://localhost:3000/api/auth/users",
							"protocol": "http",
							"host": [
								"localhost"
							],
							"port": "3000",
							"path": [
								"api",
								"auth",
								"users"
							]
						}
					},
					"response": []
				}
			]
		},
		{
			"name": "Ticket Routes",
			"item": [
				{
					"name": "create ticket",
					"request": {
						"method": "POST",
						"header": [],
						"body": {
							"mode": "raw",
							"raw": "{\r\n  \"title\": \"Next.js API Routes returning 404 after deployment\",\r\n  \"description\": \"I created custom API routes in my Next.js app under the `/app/api` directory. Everything works fine locally, but after deploying to Vercel, my API routes return 404 errors. I already checked my route structure and file names. Need help debugging this issue and understanding how Next.js handles API routing in production.\"\r\n}\r\n",
							"options": {
								"raw": {
									"language": "json"
								}
							}
						},
						"url": {
							"raw": "http://localhost:3000/api/tickets/",
							"protocol": "http",
							"host": [
								"localhost"
							],
							"port": "3000",
							"path": [
								"api",
								"tickets",
								""
							]
						}
					},
					"response": []
				},
				{
					"name": "get ticket",
					"request": {
						"method": "GET",
						"header": [],
						"url": {
							"raw": "http://localhost:3000/api/tickets/68e2ad3162f04671921f0d49",
							"protocol": "http",
							"host": [
								"localhost"
							],
							"port": "3000",
							"path": [
								"api",
								"tickets",
								"68e2ad3162f04671921f0d49"
							]
						}
					},
					"response": []
				},
				{
					"name": "get all tickets",
					"request": {
						"method": "GET",
						"header": [],
						"url": {
							"raw": "http://localhost:3000/api/tickets",
							"protocol": "http",
							"host": [
								"localhost"
							],
							"port": "3000",
							"path": [
								"api",
								"tickets"
							]
						}
					},
					"response": []
				}
			]
		}
	]
}